dagster_airlift/__init__.py
dagster_airlift/cli.py
dagster_airlift/constants.py
dagster_airlift/py.typed
dagster_airlift/version.py
dagster_airlift/core/__init__.py
dagster_airlift/core/airflow_defs_data.py
dagster_airlift/core/airflow_instance.py
dagster_airlift/core/basic_auth.py
dagster_airlift/core/dag_asset.py
dagster_airlift/core/filter.py
dagster_airlift/core/job_builder.py
dagster_airlift/core/load_defs.py
dagster_airlift/core/multiple_tasks.py
dagster_airlift/core/runtime_representations.py
dagster_airlift/core/top_level_dag_def_api.py
dagster_airlift/core/utils.py
dagster_airlift/core/components/__init__.py
dagster_airlift/core/components/airflow_instance/__init__.py
dagster_airlift/core/components/airflow_instance/component.py
dagster_airlift/core/monitoring_job/__init__.py
dagster_airlift/core/monitoring_job/builder.py
dagster_airlift/core/monitoring_job/event_stream.py
dagster_airlift/core/monitoring_job/utils.py
dagster_airlift/core/sensor/__init__.py
dagster_airlift/core/sensor/event_translation.py
dagster_airlift/core/sensor/sensor_builder.py
dagster_airlift/core/serialization/__init__.py
dagster_airlift/core/serialization/compute.py
dagster_airlift/core/serialization/defs_construction.py
dagster_airlift/core/serialization/serialized_data.py
dagster_airlift/in_airflow/__init__.py
dagster_airlift/in_airflow/base_asset_operator.py
dagster_airlift/in_airflow/dag_proxy_operator.py
dagster_airlift/in_airflow/dagster_run_utils.py
dagster_airlift/in_airflow/gql_queries.py
dagster_airlift/in_airflow/materialize_assets_operator.py
dagster_airlift/in_airflow/partition_utils.py
dagster_airlift/in_airflow/proxied_state.py
dagster_airlift/in_airflow/proxying_fn.py
dagster_airlift/in_airflow/scaffolding.py
dagster_airlift/in_airflow/task_proxy_operator.py
dagster_airlift/mwaa/__init__.py
dagster_airlift/mwaa/auth.py
dagster_airlift/test/__init__.py
dagster_airlift/test/airflow_test_instance.py
dagster_airlift/test/shared_fixtures.py
dagster_airlift-0.28.13.dist-info/licenses/LICENSE
dagster_airlift-0.28.13.dist-info/METADATA
dagster_airlift-0.28.13.dist-info/WHEEL
dagster_airlift-0.28.13.dist-info/entry_points.txt
dagster_airlift-0.28.13.dist-info/top_level.txt
dagster_airlift-0.28.13.dist-info/RECORD
